red_wine_model/__init__.py
red_wine_model/config.yml
red_wine_model/pipeline.py
red_wine_model/predict.py
red_wine_model/train_pipeline.py
red_wine_model/config/__init__.py
red_wine_model/config/core.py
red_wine_model/datasets/__init__.py
red_wine_model/processing/__init__.py
red_wine_model/processing/data_manager.py
red_wine_model/processing/validation.py
red_wine_model/trained_models/red-wine-model-outputsv0.0.1.pkl
red_wine_model_matthew9655-0.0.2.dist-info/METADATA
red_wine_model_matthew9655-0.0.2.dist-info/WHEEL
red_wine_model_matthew9655-0.0.2.dist-info/top_level.txt
red_wine_model_matthew9655-0.0.2.dist-info/RECORD
