Metadata-Version: 2.1
Name: red-wine-model-matthew9655
Version: 0.0.2
Summary: A red wine classification model
Author-email: Matthew Choi <matt.choi531@gmail.com>
Classifier: Programming Language :: Python :: 3
Classifier: Operating System :: OS Independent
Requires-Python: >=3.10
Requires-Dist: numpy
Requires-Dist: scikit-learn
Requires-Dist: typing
Requires-Dist: pandas
Requires-Dist: pydantic
Requires-Dist: strictyaml
Requires-Dist: pathlib
Provides-Extra: dev
Requires-Dist: pytest; extra == "dev"
Requires-Dist: tox; extra == "dev"
Requires-Dist: flake8; extra == "dev"
Requires-Dist: black; extra == "dev"
Requires-Dist: isort; extra == "dev"
Provides-Extra: viz
Requires-Dist: matplotlib; extra == "viz"
Requires-Dist: seaborn; extra == "viz"
